[
  {"day":7, "time":"7:00 AM",  "duration":"30 min",   "name":"Stretch & Release",                              "venue":"Fitness Center",       "deck":"9"},
  {"day":7, "time":"8:00 AM",  "duration":"16 hours", "name":"Crosswords & Number Puzzles are Available",      "venue":"Atrium",               "deck":"1"},
  {"day":7, "time":"8:00 AM",  "duration":"5 hours",  "name":"Spa Special: The Relaxation Package",            "venue":"Spa & Salon",          "deck":"9"},
  {"day":7, "time":"8:00 AM",  "duration":"1 hour",   "name":"Pure Form Yoga ($20)",                           "venue":"Fitness Center",       "deck":"9"},
  {"day":7, "time":"8:00 AM",  "duration":"1 hour",   "name":"Pickleball Open Play",                           "venue":"Sport Court",          "deck":"11"},
  {"day":7, "time":"8:00 AM",  "duration":"30 min",   "name":"Tai Chi for Everyone",                           "venue":"Lido Poolside",        "deck":"9"},
  {"day":7, "time":"9:00 AM",  "duration":null,       "name":"EFFY Outlet & Sample Sale",                      "venue":"Effy Jewelry",         "deck":"3"},
  {"day":7, "time":"9:00 AM",  "duration":"1.5 hours","name":"Designer Watches: Under $500",                   "venue":"The Shops",            "deck":"3"},
  {"day":7, "time":"9:00 AM",  "duration":"1.5 hours","name":"Designer Sunglasses: Special Offer",             "venue":"The Shops",            "deck":"3"},
  {"day":7, "time":"9:30 AM",  "duration":"45 min",   "name":"Watercoloring: Cactus",                          "venue":"Art Studio",           "deck":"10"},
  {"day":7, "time":"10:00 AM", "duration":"30 min",   "name":"Stress Relief & Longevity",                      "venue":"Spa & Salon",          "deck":"9"},
  {"day":7, "time":"10:00 AM", "duration":null,       "name":"Pickleball Tournament",                          "venue":"Sport Court",          "deck":"11"},
  {"day":7, "time":"11:00 AM", "duration":"13 hours", "name":"Crosswords & Number Puzzles are Available",      "venue":"Library",              "deck":"3"},
  {"day":7, "time":"11:00 AM", "duration":"30 min",   "name":"Complimentary Massage Sampler",                  "venue":"Spa & Salon",          "deck":"9"},
  {"day":7, "time":"11:00 AM", "duration":"45 min",   "name":"Vivace Pianist Plays",                           "venue":"Explorer's Lounge",    "deck":"2"},
  {"day":7, "time":"11:15 AM", "duration":"45 min",   "name":"Vivace Cellist Plays",                           "venue":"Ocean Bar",            "deck":"3"},
  {"day":7, "time":"11:30 AM", "duration":"30 min",   "name":"Healthy Hair Consultations",                     "venue":"Spa & Salon",          "deck":"9"},
  {"day":7, "time":"1:00 PM",  "duration":"3 hours",  "name":"Mahjong Players Meet until 4:00pm",              "venue":"Game Room",            "deck":"10"},
  {"day":7, "time":"2:00 PM",  "duration":"1.75 hours","name":"Today's Movie: Good Fortune",                   "venue":"Rolling Stone Lounge", "deck":"2"},
  {"day":7, "time":"3:00 PM",  "duration":"45 min",   "name":"Friends of Bill W. Meet",                        "venue":"Explorer's Lounge",    "deck":"2"},
  {"day":7, "time":"3:30 PM",  "duration":"45 min",   "name":"Creating Doodle Designs: Sunset",                "venue":"Art Studio",           "deck":"10"},
  {"day":7, "time":"4:00 PM",  "duration":"45 min",   "name":"Team Trivia Challenge",                          "venue":"Billboard Onboard",    "deck":"2"},
  {"day":7, "time":"4:00 PM",  "duration":"45 min",   "name":"Ping Pong Tournament",                           "venue":"Lido Poolside",        "deck":"9"},
  {"day":7, "time":"4:30 PM",  "duration":"45 min",   "name":"Origami Folding: Whale",                         "venue":"Art Studio",           "deck":"10"},
  {"day":7, "time":"5:00 PM",  "duration":"30 min",   "name":"Evening Stretch",                                "venue":"Fitness Center",       "deck":"9"},
  {"day":7, "time":"5:00 PM",  "duration":"1 hour",   "name":"Pickleball Open Play",                           "venue":"Sport Court",          "deck":"11"},
  {"day":7, "time":"7:00 PM",  "duration":"30 min",   "name":"Music Trivia: Goodbye Songs",                    "venue":"Billboard Onboard",    "deck":"2"},
  {"day":7, "time":"7:00 PM",  "duration":"45 min",   "name":"PRIDE Meetup",                                   "venue":"Gallery Bar",          "deck":"2"},
  {"day":7, "time":"7:15 PM",  "duration":"45 min",   "name":"Vivace Pianist Plays",                           "venue":"Explorer's Lounge",    "deck":"2"},
  {"day":7, "time":"8:15 PM",  "duration":"45 min",   "name":"Billboard Onboard Plays The 1960s",              "venue":"Billboard Onboard",    "deck":"2"},
  {"day":7, "time":"8:30 PM",  "duration":"45 min",   "name":"Rolling Stone Lounge Band Plays Rock the Yacht", "venue":"Rolling Stone Lounge", "deck":"2"},
  {"day":7, "time":"9:00 PM",  "duration":"45 min",   "name":"Young Adult Meetup",                             "venue":"Gallery Bar",          "deck":"2"},
  {"day":7, "time":"9:15 PM",  "duration":"45 min",   "name":"Billboard Onboard Plays One-Hit Wonders",        "venue":"Billboard Onboard",    "deck":"2"},
  {"day":7, "time":"9:30 PM",  "duration":"45 min",   "name":"Game Night: Dance Through the Decades",          "venue":"Explorer's Lounge",    "deck":"2"},
  {"day":7, "time":"9:30 PM",  "duration":"45 min",   "name":"Rolling Stone Lounge Band Plays Liverpool Sounds","venue":"Rolling Stone Lounge","deck":"2"},
  {"day":7, "time":"10:15 PM", "duration":"45 min",   "name":"Billboard Onboard Plays All Requests",           "venue":"Billboard Onboard",    "deck":"2"},
  {"day":7, "time":"10:30 PM", "duration":"45 min",   "name":"Rolling Stone Lounge Band Plays Liverpool Sounds","venue":"Rolling Stone Lounge","deck":"2"}
]
